setup.py
pollen/__init__.py
pollen/argparser.py
pollen/login_preparer.py
pollen/main.py
pollen/preparer.py
pollen/scrlogger.py
pollen/socker.py
pollen/utils.py
pollen/websocker.py
pollen/zipper.py
pollen.egg-info/PKG-INFO
pollen.egg-info/SOURCES.txt
pollen.egg-info/dependency_links.txt
pollen.egg-info/entry_points.txt
pollen.egg-info/requires.txt
pollen.egg-info/top_level.txt