Metadata-Version: 1.1
Name: pollen
Version: 0.9.9
Summary: A command-line client to the Pollen Cloud Compiler.
Home-page: https://github.com/amaret/pollenc
Author: Amaret, Inc
Author-email: develop@amaret.com
License: GPLv2
Keywords: python pollen micro-controller toolchain compiler
Platform: UNKNOWN
Classifier: Development Status :: 5 - Production/Stable
Classifier: Intended Audience :: Developers
Classifier: Natural Language :: English
Classifier: License :: OSI Approved :: GNU General Public License v2 (GPLv2)
Classifier: Topic :: Software Development :: Compilers
Classifier: Operating System :: OS Independent
Classifier: Programming Language :: Python
Classifier: Programming Language :: Python :: 2
Classifier: Programming Language :: Python :: 2.7
